icalendar-stubs/METADATA.toml
icalendar-stubs/__init__.pyi
icalendar-stubs/alarms.pyi
icalendar-stubs/attr.pyi
icalendar-stubs/cal.pyi
icalendar-stubs/caselessdict.pyi
icalendar-stubs/enums.pyi
icalendar-stubs/error.pyi
icalendar-stubs/param.pyi
icalendar-stubs/parser.pyi
icalendar-stubs/parser_tools.pyi
icalendar-stubs/prop.pyi
icalendar-stubs/py.typed
icalendar-stubs/tools.pyi
icalendar-stubs/version.pyi
icalendar-stubs/timezone/__init__.pyi
icalendar-stubs/timezone/equivalent_timezone_ids.pyi
icalendar-stubs/timezone/equivalent_timezone_ids_result.pyi
icalendar-stubs/timezone/provider.pyi
icalendar-stubs/timezone/pytz.pyi
icalendar-stubs/timezone/tzid.pyi
icalendar-stubs/timezone/tzp.pyi
icalendar-stubs/timezone/windows_to_olson.pyi
icalendar-stubs/timezone/zoneinfo.pyi
types_icalendar-6.3.2.20251222.dist-info/licenses/LICENSE
types_icalendar-6.3.2.20251222.dist-info/METADATA
types_icalendar-6.3.2.20251222.dist-info/WHEEL
types_icalendar-6.3.2.20251222.dist-info/top_level.txt
types_icalendar-6.3.2.20251222.dist-info/RECORD
